pytest_xdist_rate_limit/__init__.py
pytest_xdist_rate_limit/events.py
pytest_xdist_rate_limit/exceptions.py
pytest_xdist_rate_limit/pacer_metrics.py
pytest_xdist_rate_limit/plugin.py
pytest_xdist_rate_limit/rate.py
pytest_xdist_rate_limit/rate_limiter_fixture.py
pytest_xdist_rate_limit/rate_monitor.py
pytest_xdist_rate_limit/shared_json.py
pytest_xdist_rate_limit/token_bucket_algorithm.py
pytest_xdist_rate_limit/token_bucket_rate_limiter.py
pytest_xdist_rate_limit-1.1.0.dist-info/licenses/LICENSE
pytest_xdist_rate_limit-1.1.0.dist-info/METADATA
pytest_xdist_rate_limit-1.1.0.dist-info/WHEEL
pytest_xdist_rate_limit-1.1.0.dist-info/entry_points.txt
pytest_xdist_rate_limit-1.1.0.dist-info/top_level.txt
pytest_xdist_rate_limit-1.1.0.dist-info/RECORD
