Metadata-Version: 2.4
Name: pytest-xdist-rate-limit
Version: 1.1.0
Summary: Shared state management and rate limiting for pytest-xdist workers
Author-email: Xavier Vergés <github@verg.es>
Maintainer-email: Xavier Vergés <github@verg.es>
License: 
Project-URL: Repository, https://github.com/xverges/pytest-xdist-rate-limit
Classifier: Framework :: Pytest
Classifier: Development Status :: 4 - Beta
Classifier: Intended Audience :: Developers
Classifier: Topic :: Software Development :: Testing
Classifier: Operating System :: OS Independent
Classifier: Programming Language :: Python
Classifier: Programming Language :: Python :: 3.9
Classifier: Programming Language :: Python :: 3.10
Classifier: Programming Language :: Python :: 3.11
Classifier: Programming Language :: Python :: 3.12
Classifier: Programming Language :: Python :: 3 :: Only
Classifier: Programming Language :: Python :: Implementation :: CPython
Classifier: Programming Language :: Python :: Implementation :: PyPy
Classifier: License :: OSI Approved :: MIT License
Requires-Python: >=3.9
License-File: LICENSE
Requires-Dist: pytest>=8.4.2
Requires-Dist: pytest-xdist>=3.8.0
Requires-Dist: filelock>=3.0.0
Requires-Dist: fastdigest>=0.3.2
Provides-Extra: dev
Requires-Dist: pytest-xdist-load-testing>=0.2.0; extra == "dev"
Dynamic: license-file
